picobrew_server/__init__.py
picobrew_server/beerxml/__init__.py
picobrew_server/beerxml/picobrew_parser.py
picobrew_server/beerxml/picobrew_program_step.py
picobrew_server/beerxml/picobrew_recipe.py
picobrew_server/blueprints/__init__.py
picobrew_server/blueprints/errors.py
picobrew_server/blueprints/frontend.py
picobrew_server/blueprints/picobrew_api.py
picobrew_server/static/css/main.css
picobrew_server/static/css/materialize.min.css
picobrew_server/static/font/material-design-icons/LICENSE.txt
picobrew_server/static/font/material-design-icons/Material-Design-Icons.eot
picobrew_server/static/font/material-design-icons/Material-Design-Icons.svg
picobrew_server/static/font/material-design-icons/Material-Design-Icons.ttf
picobrew_server/static/font/material-design-icons/Material-Design-Icons.woff
picobrew_server/static/font/material-design-icons/Material-Design-Icons.woff2
picobrew_server/static/font/roboto/Roboto-Bold.ttf
picobrew_server/static/font/roboto/Roboto-Bold.woff
picobrew_server/static/font/roboto/Roboto-Bold.woff2
picobrew_server/static/font/roboto/Roboto-Light.ttf
picobrew_server/static/font/roboto/Roboto-Light.woff
picobrew_server/static/font/roboto/Roboto-Light.woff2
picobrew_server/static/font/roboto/Roboto-Medium.ttf
picobrew_server/static/font/roboto/Roboto-Medium.woff
picobrew_server/static/font/roboto/Roboto-Medium.woff2
picobrew_server/static/font/roboto/Roboto-Regular.ttf
picobrew_server/static/font/roboto/Roboto-Regular.woff
picobrew_server/static/font/roboto/Roboto-Regular.woff2
picobrew_server/static/font/roboto/Roboto-Thin.ttf
picobrew_server/static/font/roboto/Roboto-Thin.woff
picobrew_server/static/font/roboto/Roboto-Thin.woff2
picobrew_server/static/img/LICENSE.txt
picobrew_server/static/img/android-icon-144x144.png
picobrew_server/static/img/android-icon-192x192.png
picobrew_server/static/img/android-icon-36x36.png
picobrew_server/static/img/android-icon-48x48.png
picobrew_server/static/img/android-icon-72x72.png
picobrew_server-1.0.1.dist-info/LICENSE
picobrew_server-1.0.1.dist-info/WHEEL
picobrew_server-1.0.1.dist-info/METADATA
picobrew_server-1.0.1.dist-info/RECORD
